<?xml version="1.0"?>
<Ontology version="2">
<Instances>
<Instance name="program1">
      <DirectSuperConcepts>
        <ConceptReference name="program" />
      </DirectSuperConcepts>
      <documentation value="" />
      <NLInfo>
        <LexicalInfo />
        <NLPattern>
          <Fragments>
            <OntologyEntity>
              <InstanceReference name="program1" />
            </OntologyEntity>
          </Fragments>
        </NLPattern>
        <NLPattern>
          <Fragments />
        </NLPattern>
      </NLInfo>
    </Instance>
<Instance name="source port1">
      <DirectSuperConcepts>
        <ConceptReference name="port" />
      </DirectSuperConcepts>
      <documentation value="" />
      <NLInfo>
        <LexicalInfo />
        <NLPattern>
          <Fragments>
            <OntologyEntity>
              <InstanceReference name="source port1" />
            </OntologyEntity>
          </Fragments>
        </NLPattern>
        <NLPattern>
          <Fragments />
        </NLPattern>
      </NLInfo>
    </Instance>
<Instance name="time1">
      <DirectSuperConcepts>
        <ConceptReference name="time" />
      </DirectSuperConcepts>
      <documentation value="" />
      <NLInfo>
        <LexicalInfo />
        <NLPattern>
          <Fragments>
            <OntologyEntity>
              <InstanceReference name="time1" />
            </OntologyEntity>
          </Fragments>
        </NLPattern>
        <NLPattern>
          <Fragments />
        </NLPattern>
      </NLInfo>
    </Instance>
<Instance name="domain1">
      <DirectSuperConcepts>
        <ConceptReference name="domain" />
      </DirectSuperConcepts>
      <documentation value="" />
      <NLInfo>
        <LexicalInfo />
        <NLPattern>
          <Fragments>
            <OntologyEntity>
              <InstanceReference name="domain1" />
            </OntologyEntity>
          </Fragments>
        </NLPattern>
        <NLPattern>
          <Fragments />
        </NLPattern>
      </NLInfo>
    </Instance>
<Instance name="IP address mapping1">
      <DirectSuperConcepts>
        <ConceptReference name="IP address mapping" />
      </DirectSuperConcepts>
      <documentation value="" />
      <NLInfo>
        <LexicalInfo />
        <NLPattern>
          <Fragments>
            <OntologyEntity>
              <InstanceReference name="IP address mapping1" />
            </OntologyEntity>
          </Fragments>
        </NLPattern>
        <NLPattern>
          <Fragments />
        </NLPattern>
      </NLInfo>
    </Instance>
<Instance name="APT28">
      <DirectSuperConcepts>
        <ConceptReference name="APT group" />
      </DirectSuperConcepts>
      <documentation value="" />
      <NLInfo>
        <LexicalInfo />
        <NLPattern>
          <Fragments>
            <OntologyEntity>
              <InstanceReference name="APT28" />
            </OntologyEntity>
          </Fragments>
        </NLPattern>
        <NLPattern>
          <Fragments />
        </NLPattern>
      </NLInfo>
    </Instance>
<Instance name="DNS registrar1">
      <DirectSuperConcepts>
        <ConceptReference name="DNS provider" />
      </DirectSuperConcepts>
      <documentation value="" />
      <NLInfo>
        <LexicalInfo />
        <NLPattern>
          <Fragments>
            <OntologyEntity>
              <InstanceReference name="DNS registrar1" />
            </OntologyEntity>
          </Fragments>
        </NLPattern>
        <NLPattern>
          <Fragments />
        </NLPattern>
      </NLInfo>
    </Instance>
<Instance name="destination port1">
      <DirectSuperConcepts>
        <ConceptReference name="DNS port" />
      </DirectSuperConcepts>
      <documentation value="" />
      <NLInfo>
        <LexicalInfo />
        <NLPattern>
          <Fragments>
            <OntologyEntity>
              <InstanceReference name="destination port1" />
            </OntologyEntity>
          </Fragments>
        </NLPattern>
        <NLPattern>
          <Fragments />
        </NLPattern>
      </NLInfo>
    </Instance>
<Instance name="destination IP1">
      <DirectSuperConcepts>
        <ConceptReference name="IPv4 address" />
      </DirectSuperConcepts>
      <documentation value="" />
      <NLInfo>
        <LexicalInfo />
        <NLPattern>
          <Fragments>
            <OntologyEntity>
              <InstanceReference name="destination IP1" />
            </OntologyEntity>
          </Fragments>
        </NLPattern>
        <NLPattern>
          <Fragments />
        </NLPattern>
      </NLInfo>
    </Instance>
<Instance name="source IP1">
      <DirectSuperConcepts>
        <ConceptReference name="IPv4 address" />
      </DirectSuperConcepts>
      <documentation value="" />
      <NLInfo>
        <LexicalInfo />
        <NLPattern>
          <Fragments>
            <OntologyEntity>
              <InstanceReference name="source IP1" />
            </OntologyEntity>
          </Fragments>
        </NLPattern>
        <NLPattern>
          <Fragments />
        </NLPattern>
      </NLInfo>
    </Instance>
<Instance name="connection1">
      <DirectSuperConcepts>
        <ConceptReference name="outbound connection" />
      </DirectSuperConcepts>
      <documentation value="" />
      <NLInfo>
        <LexicalInfo />
        <NLPattern>
          <Fragments>
            <OntologyEntity>
              <InstanceReference name="connection1" />
            </OntologyEntity>
          </Fragments>
        </NLPattern>
        <NLPattern>
          <Fragments />
        </NLPattern>
      </NLInfo>
    </Instance>
<Instance name="reg utility">
      <DirectSuperConcepts>
        <ConceptReference name="utility software" />
      </DirectSuperConcepts>
      <documentation value="" />
      <NLInfo>
        <LexicalInfo />
        <NLPattern>
          <Fragments>
            <OntologyEntity>
              <InstanceReference name="reg utility" />
            </OntologyEntity>
          </Fragments>
        </NLPattern>
        <NLPattern>
          <Fragments />
        </NLPattern>
      </NLInfo>
    </Instance>
</Instances>
<Facts>
<Fact>
      <FeatureReference name="has as external name" />
      <ConstantInstantiatedFormalParameters>
        <FormalParameterReference name="&lt;P1>" />
        <InstanceReference name="reg utility" />
        <FormalParameterReference name="&lt;P2>" />
        <OntologyString>reg.exe</OntologyString>
      </ConstantInstantiatedFormalParameters>
    </Fact>
<Fact>
      <FeatureReference name="has as external name" />
      <ConstantInstantiatedFormalParameters>
        <FormalParameterReference name="&lt;P1>" />
        <InstanceReference name="program1" />
        <FormalParameterReference name="&lt;P2>" />
        <OntologyString>svchost.exe</OntologyString>
      </ConstantInstantiatedFormalParameters>
    </Fact>
<Fact>
      <FeatureReference name="has as external name" />
      <ConstantInstantiatedFormalParameters>
        <FormalParameterReference name="&lt;P1>" />
        <InstanceReference name="IP address mapping1" />
        <FormalParameterReference name="&lt;P2>" />
        <OntologyString>69.195.129.72</OntologyString>
      </ConstantInstantiatedFormalParameters>
    </Fact>
<Fact>
      <FeatureReference name="has as external name" />
      <ConstantInstantiatedFormalParameters>
        <FormalParameterReference name="&lt;P1>" />
        <InstanceReference name="time1" />
        <FormalParameterReference name="&lt;P2>" />
        <OntologyString>01/04/2019 15:42:57 PM</OntologyString>
      </ConstantInstantiatedFormalParameters>
    </Fact>
<Fact>
      <FeatureReference name="has as external name" />
      <ConstantInstantiatedFormalParameters>
        <FormalParameterReference name="&lt;P1>" />
        <InstanceReference name="domain1" />
        <FormalParameterReference name="&lt;P2>" />
        <OntologyString>a-jsm.infobusinessus.org</OntologyString>
      </ConstantInstantiatedFormalParameters>
    </Fact>
<Fact>
      <FeatureReference name="has as external name" />
      <ConstantInstantiatedFormalParameters>
        <FormalParameterReference name="&lt;P1>" />
        <InstanceReference name="destination port1" />
        <FormalParameterReference name="&lt;P2>" />
        <OntologyString>53</OntologyString>
      </ConstantInstantiatedFormalParameters>
    </Fact>
<Fact>
      <FeatureReference name="has as external name" />
      <ConstantInstantiatedFormalParameters>
        <FormalParameterReference name="&lt;P1>" />
        <InstanceReference name="destination IP1" />
        <FormalParameterReference name="&lt;P2>" />
        <OntologyString>10.10.4.101</OntologyString>
      </ConstantInstantiatedFormalParameters>
    </Fact>
<Fact>
      <FeatureReference name="has as external name" />
      <ConstantInstantiatedFormalParameters>
        <FormalParameterReference name="&lt;P1>" />
        <InstanceReference name="source port1" />
        <FormalParameterReference name="&lt;P2>" />
        <OntologyString>60067</OntologyString>
      </ConstantInstantiatedFormalParameters>
    </Fact>
<Fact>
      <FeatureReference name="has as external name" />
      <ConstantInstantiatedFormalParameters>
        <FormalParameterReference name="&lt;P1>" />
        <InstanceReference name="source IP1" />
        <FormalParameterReference name="&lt;P2>" />
        <OntologyString>10.10.1.11</OntologyString>
      </ConstantInstantiatedFormalParameters>
    </Fact>
<Fact>
      <FeatureReference name="has as external name" />
      <ConstantInstantiatedFormalParameters>
        <FormalParameterReference name="&lt;P1>" />
        <InstanceReference name="DNS registrar1" />
        <FormalParameterReference name="&lt;P2>" />
        <OntologyString>NOT_FOUND</OntologyString>
      </ConstantInstantiatedFormalParameters>
    </Fact>
<Fact>
      <FeatureReference name="has as IP address mapping" />
      <ConstantInstantiatedFormalParameters>
        <FormalParameterReference name="&lt;P1>" />
        <InstanceReference name="domain1" />
        <FormalParameterReference name="&lt;P2>" />
        <InstanceReference name="IP address mapping1" />
      </ConstantInstantiatedFormalParameters>
    </Fact>
<Fact>
      <FeatureReference name="has as DNS registrar" />
      <ConstantInstantiatedFormalParameters>
        <FormalParameterReference name="&lt;P1>" />
        <InstanceReference name="domain1" />
        <FormalParameterReference name="&lt;P2>" />
        <InstanceReference name="DNS registrar1" />
      </ConstantInstantiatedFormalParameters>
    </Fact>
<Fact>
      <FeatureReference name="has as process ID" />
      <ConstantInstantiatedFormalParameters>
        <FormalParameterReference name="&lt;P1>" />
        <InstanceReference name="program1" />
        <FormalParameterReference name="&lt;P2>" />
        <OntologyString>2064</OntologyString>
      </ConstantInstantiatedFormalParameters>
    </Fact>
<Fact>
      <FeatureReference name="has as path name" />
      <ConstantInstantiatedFormalParameters>
        <FormalParameterReference name="&lt;P1>" />
        <InstanceReference name="program1" />
        <FormalParameterReference name="&lt;P2>" />
        <OntologyString>C:\Windows\Temp\svchost.exe</OntologyString>
      </ConstantInstantiatedFormalParameters>
    </Fact>
<Fact>
      <FeatureReference name="has as temporary folder" />
      <ConstantInstantiatedFormalParameters>
        <FormalParameterReference name="&lt;P1>" />
        <InstanceReference name="source IP1" />
        <FormalParameterReference name="&lt;P2>" />
        <InstanceReference name="Auriga temporary folder1" />
      </ConstantInstantiatedFormalParameters>
    </Fact>
<Fact>
      <FeatureReference name="has as temporary file" />
      <ConstantInstantiatedFormalParameters>
        <FormalParameterReference name="&lt;P1>" />
        <InstanceReference name="source IP1" />
        <FormalParameterReference name="&lt;P2>" />
        <InstanceReference name="Auriga temporary file1" />
      </ConstantInstantiatedFormalParameters>
    </Fact>
<Fact>
      <FeatureReference name="has as data file" />
      <ConstantInstantiatedFormalParameters>
        <FormalParameterReference name="&lt;P1>" />
        <InstanceReference name="source IP1" />
        <FormalParameterReference name="&lt;P2>" />
        <InstanceReference name="Auriga data file2" />
      </ConstantInstantiatedFormalParameters>
    </Fact>
<Fact>
      <FeatureReference name="has as data file" />
      <ConstantInstantiatedFormalParameters>
        <FormalParameterReference name="&lt;P1>" />
        <InstanceReference name="source IP1" />
        <FormalParameterReference name="&lt;P2>" />
        <InstanceReference name="Auriga data file1" />
      </ConstantInstantiatedFormalParameters>
    </Fact>
<Fact>
      <FeatureReference name="has as library file" />
      <ConstantInstantiatedFormalParameters>
        <FormalParameterReference name="&lt;P1>" />
        <InstanceReference name="source IP1" />
        <FormalParameterReference name="&lt;P2>" />
        <InstanceReference name="Auriga library file1" />
      </ConstantInstantiatedFormalParameters>
    </Fact>
<Fact>
      <FeatureReference name="has as library file" />
      <ConstantInstantiatedFormalParameters>
        <FormalParameterReference name="&lt;P1>" />
        <InstanceReference name="source IP1" />
        <FormalParameterReference name="&lt;P2>" />
        <InstanceReference name="Auriga DLL1" />
      </ConstantInstantiatedFormalParameters>
    </Fact>
<Fact>
      <FeatureReference name="has as command shell file" />
      <ConstantInstantiatedFormalParameters>
        <FormalParameterReference name="&lt;P1>" />
        <InstanceReference name="source IP1" />
        <FormalParameterReference name="&lt;P2>" />
        <InstanceReference name="Auriga command shell file2" />
      </ConstantInstantiatedFormalParameters>
    </Fact>
<Fact>
      <FeatureReference name="has as command shell file" />
      <ConstantInstantiatedFormalParameters>
        <FormalParameterReference name="&lt;P1>" />
        <InstanceReference name="source IP1" />
        <FormalParameterReference name="&lt;P2>" />
        <InstanceReference name="Auriga command shell file1" />
      </ConstantInstantiatedFormalParameters>
    </Fact>
<Fact>
      <FeatureReference name="has as Registry key" />
      <ConstantInstantiatedFormalParameters>
        <FormalParameterReference name="&lt;P1>" />
        <InstanceReference name="source IP1" />
        <FormalParameterReference name="&lt;P2>" />
        <InstanceReference name="Auriga Registry key1" />
      </ConstantInstantiatedFormalParameters>
    </Fact>
<Fact>
      <FeatureReference name="has as Registry key" />
      <ConstantInstantiatedFormalParameters>
        <FormalParameterReference name="&lt;P1>" />
        <InstanceReference name="source IP1" />
        <FormalParameterReference name="&lt;P2>" />
        <InstanceReference name="Auriga Registry key2" />
      </ConstantInstantiatedFormalParameters>
    </Fact>
</Facts>
</Ontology>